odoo/addons/l10n_br_sale_commission_stock/README.rst
odoo/addons/l10n_br_sale_commission_stock/__init__.py
odoo/addons/l10n_br_sale_commission_stock/__manifest__.py
odoo/addons/l10n_br_sale_commission_stock/demo/sale_order.xml
odoo/addons/l10n_br_sale_commission_stock/i18n/l10n_br_sale_commission_stock.pot
odoo/addons/l10n_br_sale_commission_stock/readme/CONFIGURE.rst
odoo/addons/l10n_br_sale_commission_stock/readme/CONTRIBUTORS.rst
odoo/addons/l10n_br_sale_commission_stock/readme/CREDITS.rst
odoo/addons/l10n_br_sale_commission_stock/readme/DESCRIPTION.rst
odoo/addons/l10n_br_sale_commission_stock/readme/HISTORY.rst
odoo/addons/l10n_br_sale_commission_stock/readme/INSTALL.rst
odoo/addons/l10n_br_sale_commission_stock/readme/ROADMAP.rst
odoo/addons/l10n_br_sale_commission_stock/readme/USAGE.rst
odoo/addons/l10n_br_sale_commission_stock/readme/static/description/icon.png
odoo/addons/l10n_br_sale_commission_stock/readme/static/description/index.html
odoo/addons/l10n_br_sale_commission_stock/static/description/icon.png
odoo/addons/l10n_br_sale_commission_stock/static/description/index.html
odoo/addons/l10n_br_sale_commission_stock/tests/__init__.py
odoo/addons/l10n_br_sale_commission_stock/tests/test_sale_commission_stock.py
odoo/addons/l10n_br_sale_commission_stock/wizards/__init__.py
odoo/addons/l10n_br_sale_commission_stock/wizards/stock_invoice_onshipping.py
odoo12_addon_l10n_br_sale_commission_stock-12.0.1.0.0.99.dev4.dist-info/METADATA
odoo12_addon_l10n_br_sale_commission_stock-12.0.1.0.0.99.dev4.dist-info/WHEEL
odoo12_addon_l10n_br_sale_commission_stock-12.0.1.0.0.99.dev4.dist-info/top_level.txt
odoo12_addon_l10n_br_sale_commission_stock-12.0.1.0.0.99.dev4.dist-info/RECORD
